mongrey/__init__.py
mongrey/version.py
mongrey/constants.py
mongrey/utils.py
mongrey/cache.py
mongrey/policy.py
mongrey/exceptions.py
mongrey/validators.py
mongrey/mongrey_test.db
mongrey/translations/__init__.py
mongrey/translations/babel.cfg
mongrey/translations/mongrey.pot
mongrey/translations/fr/LC_MESSAGES/messages.mo
mongrey/translations/fr/LC_MESSAGES/messages.po
mongrey/api/__init__.py
mongrey/api/mongo.py
mongrey/api/base.py
mongrey/api/sql.py
mongrey/ext/__init__.py
mongrey/ext/flask_login.py
mongrey/ext/geoip_data.py
mongrey/ext/GeoIP.dat
mongrey/ext/GeoIPv6.dat
mongrey/ext/slugify/__init__.py
mongrey/ext/slugify/alt_translates.py
mongrey/ext/slugify/main.py
mongrey/ext/slugify/slugify.py
mongrey/ext/slugify/tests.py
mongrey/helpers/__init__.py
mongrey/helpers/check_dnsl.py
mongrey/helpers/check_fqdn.py
mongrey/helpers/check_rfc.py
mongrey/helpers/check_spf.py
mongrey/migration/__init__.py
mongrey/migration/utils.py
mongrey/migration/radicalspam.py
mongrey/migration/core.py
mongrey/install/__init__.py
mongrey/install/core.py
mongrey/install/resources/__init__.py
mongrey/install/resources/initd/__init__.py
mongrey/install/resources/initd/system5/__init__.py
mongrey/install/resources/initd/system5/mongrey-server.j2
mongrey/install/resources/fail2ban/__init__.py
mongrey/install/resources/fail2ban/fail2ban.conf.j2
mongrey/install/resources/fail2ban/jail-mongrey.conf.j2
mongrey/install/resources/supervisord/__init__.py
mongrey/install/resources/supervisord/mongrey.conf.j2
mongrey/install/resources/supervisord/supervisord.conf.j2
mongrey/storage/__init__.py
mongrey/storage/base.py
mongrey/storage/sql/__init__.py
mongrey/storage/sql/models.py
mongrey/storage/sql/admin.py
mongrey/storage/sql/policy.py
mongrey/storage/mongo/__init__.py
mongrey/storage/mongo/models.py
mongrey/storage/mongo/admin.py
mongrey/storage/mongo/utils.py
mongrey/storage/mongo/policy.py
mongrey/server/__init__.py
mongrey-0.4.4.dist-info/top_level.txt
mongrey-0.4.4.dist-info/entry_points.txt
mongrey-0.4.4.dist-info/pbr.json
mongrey-0.4.4.dist-info/METADATA
mongrey-0.4.4.dist-info/DESCRIPTION.rst
mongrey-0.4.4.dist-info/metadata.json
mongrey-0.4.4.dist-info/WHEEL
mongrey-0.4.4.dist-info/RECORD
